model/__init__.py
model/deep_ensemble.py
model/models.py
model/yolo_layer.py
utilz/__init__.py
utilz/torch_utils.py
utilz/utils.py
Yolo_Distribution_Distillation_Demo-1.0.1.dist-info/METADATA
Yolo_Distribution_Distillation_Demo-1.0.1.dist-info/WHEEL
Yolo_Distribution_Distillation_Demo-1.0.1.dist-info/top_level.txt
Yolo_Distribution_Distillation_Demo-1.0.1.dist-info/RECORD
