Metadata-Version: 2.1
Name: Yolo-Distribution-Distillation-Demo
Version: 1.0.1
Summary: Run inference on Yolo Distribution Distillation model.
Home-page: UNKNOWN
Author: Maximilian Henne
Author-email: maximilian.henne@iks.fraunhofer.de
License: Apache
Platform: UNKNOWN
Classifier: License :: OSI Approved :: Apache Software License
Classifier: Programming Language :: Python :: 3
Requires-Python: >=3.6
Requires-Dist: torch (==1.6.0)
Requires-Dist: torchvision (==0.7.0)
Requires-Dist: numpy (==1.18.2)
Requires-Dist: opencv-python (==4.4.0.42)
Requires-Dist: pycocotools (==2.0.1)
Requires-Dist: matplotlib (==3.3.1)
